lvfs_mirror/__init__.py
lvfs_mirror/__main__.py
lvfs_mirror/config.py
lvfs_mirror/jcat.py
lvfs_mirror/lvfs_mirror.py
lvfs_mirror/utils.py
lvfs_mirror-0.3.3.dist-info/LICENSE.txt
lvfs_mirror-0.3.3.dist-info/METADATA
lvfs_mirror-0.3.3.dist-info/WHEEL
lvfs_mirror-0.3.3.dist-info/entry_points.txt
lvfs_mirror-0.3.3.dist-info/RECORD
