Metadata-Version: 2.1
Name: lvfs-mirror
Version: 0.3.3
Summary: Mirror for LVFS repositories (used for fwupd).
License: MIT
Author: Sebastian Endres
Author-email: dev@sedrubal.de
Requires-Python: >=3.11,<4.0
Classifier: License :: OSI Approved :: MIT License
Classifier: Programming Language :: Python :: 3
Classifier: Programming Language :: Python :: 3.11
Classifier: Programming Language :: Python :: 3.12
Requires-Dist: packaging (>=23.0,<24.0)
Requires-Dist: pyxattr (>=0.7.2,<0.8.0)
Requires-Dist: urllib3 (>=2.2.3,<3.0.0)
